instasele/__init__.py
instasele/client.py
instasele/logger.py
instasele/methods/__init__.py
instasele/methods/actions/__init__.py
instasele/methods/actions/comment.py
instasele/methods/actions/follow.py
instasele/methods/actions/like.py
instasele/methods/login/__init__.py
instasele/methods/login/cookies.py
instasele/methods/login/login.py
instasele/utils/__init__.py
instasele/utils/get_element_by_child.py
instasele/utils/helpers.py
instasele-1.0.0.dist-info/LICENSE
instasele-1.0.0.dist-info/METADATA
instasele-1.0.0.dist-info/WHEEL
instasele-1.0.0.dist-info/top_level.txt
instasele-1.0.0.dist-info/RECORD
