Metadata-Version: 2.1
Name: instasele
Version: 1.0.0
Summary: Simple Instagram Accounts Controller Using Selenium
Home-page: https://github.com/sa3ed7asan/instasele
Author: Al-Saeed Hasan
Author-email: Sa3ed7asanOfficial@gmail.com
License: MIT
Keywords: instagram-scraper,instagram-bot,instasele,instagram-bot-using-selenium
Classifier: Development Status :: 3 - Alpha
Classifier: Intended Audience :: Developers
Classifier: Topic :: Software Development :: Build Tools
Classifier: License :: OSI Approved :: MIT License
Classifier: Natural Language :: Indonesian
Classifier: Programming Language :: Python :: 3
Classifier: Programming Language :: Python :: 3.7
Classifier: Programming Language :: Python :: 3.8
Classifier: Programming Language :: Python :: 3.9
Classifier: Programming Language :: Python :: 3.10
Classifier: Programming Language :: Python :: 3.11
Classifier: Programming Language :: Python :: 3 :: Only
Requires-Python: >=3.9
License-File: LICENSE
Requires-Dist: selenium==4.9.1
Requires-Dist: webdriver-manager
